LICENSE
MANIFEST.in
README.md
README_en.md
setup.py
bytepiece/__init__.py
bytepiece/bytepiece.py
bytepiece/faster.c
bytepiece/faster.pyx
bytepiece.egg-info/PKG-INFO
bytepiece.egg-info/SOURCES.txt
bytepiece.egg-info/dependency_links.txt
bytepiece.egg-info/requires.txt
bytepiece.egg-info/top_level.txt