Metadata-Version: 2.1
Name: bytepiece
Version: 0.6.1
Summary: Smarter Byte-based Tokenizer
Home-page: https://github.com/bojone/bytepiece
Author: bojone
Author-email: bojone@spaces.ac.cn
License: Apache License 2.0
Requires-Python: >=3
License-File: LICENSE
